[
    {
        "Number": "101",
        "StartStop": "Центральная площадь",
        "EndStop": "Автовокзал",
        "Sign": {
            "SignNumber": "№101",
            "SignStartStop": "Центральная площадь (вокзал)",
            "SignEndStop": "Автовокзал №1"
        },
        "SignBind": "/do На передней панели установлена табличка с маршрутом 101: Центральная площадь - Автовокзал.",
        "RouteBind": [
            {
                "StopName": "Центральная площадь",
                "StopID": 1,
                "Announcement": "/do Автобус прибывает на Центральную площадь."
            },
            {
                "StopName": "Парк Победы",
                "StopID": 2,
                "Announcement": "/do Следующая остановка: Парк Победы."
            },
            {
                "StopName": "Автовокзал",
                "StopID": 3,
                "Announcement": "/do Автобус прибывает на Автовокзал."
            }
        ]
    }
]
